carde/__init__.py
carde/_version.py
carde/image_processing.py
carde/io.py
carde-0.2.1.dist-info/LICENSE
carde-0.2.1.dist-info/METADATA
carde-0.2.1.dist-info/WHEEL
carde-0.2.1.dist-info/entry_points.txt
carde-0.2.1.dist-info/top_level.txt
carde-0.2.1.dist-info/RECORD
