Metadata-Version: 2.2
Name: carde
Version: 0.2.1
Summary: Carbide Detection Tool
Author-email: Till Korten <t.korten@hzdr.de>
License: BSD-3-Clause
Keywords: image segmentation,python,scanning electron microscopy,carbide detection
Classifier: Programming Language :: Python :: 3
Requires-Python: >=3.9
License-File: LICENSE
Requires-Dist: nc_py_api
Requires-Dist: numpy
Requires-Dist: pandas
Requires-Dist: SimpleITK
Requires-Dist: scikit-image
Requires-Dist: scikit-learn
Requires-Dist: jupyterlab
Requires-Dist: stackview
Requires-Dist: seaborn
Requires-Dist: natsort
Requires-Dist: click
Provides-Extra: dev
Requires-Dist: pytest; extra == "dev"
